README.md
setup.py
cptools/__init__.py
cptools/function.py
cptools/logger.py
cptools.egg-info/PKG-INFO
cptools.egg-info/SOURCES.txt
cptools.egg-info/dependency_links.txt
cptools.egg-info/requires.txt
cptools.egg-info/top_level.txt