Metadata-Version: 2.1
Name: cptools
Version: 2.0.1
Summary: Tools used by CP
Home-page: https://github.com/GentleCP/cptools
Author: GentleCP
Author-email: me@gentlecp.com
License: UNKNOWN
Platform: any
Classifier: Programming Language :: Python :: 3
Classifier: License :: OSI Approved :: GNU General Public License (GPL)
Classifier: Operating System :: OS Independent
